{
    "Blumens": {
        "cycle": 2,
        "last_death": null,
        "alerted": false,
        "location": "Easy Marianndel-5",
        "image": "images/Blumens.webp",
        "base_time": {
            "hour": 23,
            "minute": 15,
            "second": 0
        }
    },
    "Betalanse": {
        "cycle": 2,
        "last_death": null,
        "alerted": false,
        "location": "Easy Carrotova-5",
        "image": "images/Betalanse.webp",
        "base_time": {
            "hour": 22,
            "minute": 0,
            "second": 0
        }
    },
    "Cryo": {
        "cycle": 4,
        "last_death": null,
        "alerted": false,
        "location": "Easy Acryos-5",
        "image": "images/Cryo.webp",
        "base_time": {
            "hour": 0,
            "minute": 5,
            "second": 0
        }
    },
    "Sporelex": {
        "cycle": 4,
        "last_death": null,
        "alerted": false,
        "location": "Easy Luminospore-5",
        "image": "images/Sporelex.webp",
        "base_time": {
            "hour": 23,
            "minute": 10,
            "second": 0
        }
    },
    "Toxspore": {
        "cycle": 4,
        "last_death": null,
        "alerted": false,
        "location": "Normal Cryptospora-5",
        "image": "images/Toxspore.webp",
        "base_time": {
            "hour": 23,
            "minute": 20,
            "second": 0
        }
    },
    "Bristol": {
        "cycle": 6,
        "last_death": null,
        "alerted": false,
        "location": "Normal Silavar-5",
        "image": "images/Bristol.webp",
        "base_time": {
            "hour": 1,
            "minute": 25,
            "second": 0
        }
    },
    "Veilian": {
        "cycle": 8,
        "last_death": null,
        "alerted": false,
        "location": "Normal Mortaris-5",
        "image": "images/Veilian.webp",
        "base_time": {
            "hour": 0,
            "minute": 25,
            "second": 0
        }
    },
    "Arque": {
        "cycle": 8,
        "last_death": null,
        "alerted": false,
        "location": "Normal Astreon-5",
        "image": "images/Arque.webp",
        "base_time": {
            "hour": 1,
            "minute": 35,
            "second": 0
        }
    },
    "Rootrus": {
        "cycle": 10,
        "last_death": null,
        "alerted": false,
        "location": "Normal Flameron-5",
        "image": "images/Rootrus.webp",
        "base_time": {
            "hour": 22,
            "minute": 40,
            "second": 0
        }
    },
    "Sapphire blade": {
        "cycle": 10,
        "last_death": null,
        "alerted": false,
        "location": "Normal Noxmar-5",
        "image": "images/Sapphire_blade.webp",
        "base_time": {
            "hour": 23,
            "minute": 45,
            "second": 0
        }
    },
    "Coralisk": {
        "cycle": 12,
        "last_death": null,
        "alerted": false,
        "location": "Normal Corallia-5",
        "image": "images/Coralisk.webp",
        "base_time": {
            "hour": 23,
            "minute": 50,
            "second": 0
        }
    },
    "Breeze": {
        "cycle": 12,
        "last_death": null,
        "alerted": false,
        "location": "Easy Ventera-5",
        "image": "images/Breeze.webp",
        "base_time": {
            "hour": 2,
            "minute": 5,
            "second": 0
        }
    }
} 